gsplot/__init__.py
gsplot/base/base.py
gsplot/base/base_alias_validator.py
gsplot/color/colormap.py
gsplot/config/config.py
gsplot/data/load_file.py
gsplot/figure/axes.py
gsplot/figure/axes_base.py
gsplot/figure/axes_inset.py
gsplot/figure/axes_range_base.py
gsplot/figure/figure_tools.py
gsplot/figure/show.py
gsplot/figure/store.py
gsplot/hello_world/hello_world.py
gsplot/logger.py
gsplot/path/path.py
gsplot/plot/line.py
gsplot/plot/line_base.py
gsplot/plot/line_colormap_base.py
gsplot/plot/line_colormap_dashed.py
gsplot/plot/line_colormap_solid.py
gsplot/plot/scatter.py
gsplot/plot/scatter_colormap.py
gsplot/style/graph.py
gsplot/style/label.py
gsplot/style/legend.py
gsplot/style/legend_colormap.py
gsplot/style/ticks.py
gsplot/style/title.py
gsplot/version.py
gsplot-0.2.0.dist-info/LICENSE
gsplot-0.2.0.dist-info/METADATA
gsplot-0.2.0.dist-info/WHEEL
gsplot-0.2.0.dist-info/RECORD
