Metadata-Version: 2.3
Name: gsplot
Version: 0.2.0
Summary: General-scientific plot based on matplotlib
Author: Giordano Mattoni
Author-email: mattoni@scphys.kyoto-u.ac.jp
Requires-Python: >=3.10
Classifier: Programming Language :: Python :: 3
Classifier: Programming Language :: Python :: 3.10
Classifier: Programming Language :: Python :: 3.11
Classifier: Programming Language :: Python :: 3.12
Classifier: Programming Language :: Python :: 3.13
Requires-Dist: matplotlib (>=3.9.0)
Requires-Dist: numpy (>=1.26.4)
Requires-Dist: pyyaml (>=6.0.2)
Requires-Dist: rich (>=13.9.4)
Requires-Dist: types-pyyaml (>=6.0.12.20240917)
Project-URL: Homepage, https://soichiroyamane.github.io/gsplot/
